mean_variance_portfolio-1.0.0.dist-info/DESCRIPTION.rst
mean_variance_portfolio-1.0.0.dist-info/METADATA
mean_variance_portfolio-1.0.0.dist-info/RECORD
mean_variance_portfolio-1.0.0.dist-info/WHEEL
mean_variance_portfolio-1.0.0.dist-info/metadata.json
mean_variance_portfolio-1.0.0.dist-info/top_level.txt
mvport/__init__.py
mvport/portfolio.py
mvport/stock.py
mvport/utils.py
