Metadata-Version: 2.0
Name: mean-variance-portfolio
Version: 1.0.0
Summary: MV Port is a Python package to perform Mean-Variance Analysis. It provides a Portfolio class with a variety of methods to help on your portfolio optimization tasks.
Home-page: https://github.com/condereis/mean-variance-portfolio
Author: Rafael Lopes Conde dos Reis
Author-email: rafael.lcreis@gmail.com
License: MIT license
Keywords: mvport
Platform: UNKNOWN
Classifier: Development Status :: 2 - Pre-Alpha
Classifier: Intended Audience :: Developers
Classifier: License :: OSI Approved :: MIT License
Classifier: Natural Language :: English
Classifier: Programming Language :: Python :: 2
Classifier: Programming Language :: Python :: 2.7
Classifier: Programming Language :: Python :: 3
Classifier: Programming Language :: Python :: 3.4
Classifier: Programming Language :: Python :: 3.5
Classifier: Programming Language :: Python :: 3.6
Requires-Dist: cvxopt (==1.2.0)
Requires-Dist: numpy (==1.14.5)
Requires-Dist: scipy (==1.1.0)
